{"format":1,"version":"4.5","settings":"92339c3b011832c3a0ce3c490ed719cd","files":{"MythTV___init___py":{"hash":"85a4a7782ed4101c0abc8f8dcb3c1ad2","index":{"nums":[1,20,0,0,0,0,0],"html_filename":"MythTV___init___py.html","relative_filename":"MythTV/__init__.py"}},"MythTV__conn_mysqldb_py":{"hash":"9128c258c430cb44171c28cb4474ca70","index":{"nums":[1,59,0,7,20,5,5],"html_filename":"MythTV__conn_mysqldb_py.html","relative_filename":"MythTV/_conn_mysqldb.py"}},"MythTV__conn_oursql_py":{"hash":"e32d2c6af9b06967e7107cbacd02dac5","index":{"nums":[1,37,0,33,12,0,12],"html_filename":"MythTV__conn_oursql_py.html","relative_filename":"MythTV/_conn_oursql.py"}},"MythTV_altdict_py":{"hash":"cb86d6c0b91fd77ada006a6e21515b04","index":{"nums":[1,169,0,38,59,7,13],"html_filename":"MythTV_altdict_py.html","relative_filename":"MythTV/altdict.py"}},"MythTV_connections_py":{"hash":"175c0e15e800b75bbdac07ba4719f288","index":{"nums":[1,423,0,140,125,21,61],"html_filename":"MythTV_connections_py.html","relative_filename":"MythTV/connections.py"}},"MythTV_database_py":{"hash":"08b7c4764451393b8530e3913ad35603","index":{"nums":[1,894,0,210,421,53,131],"html_filename":"MythTV_database_py.html","relative_filename":"MythTV/database.py"}},"MythTV_dataheap_py":{"hash":"dac062a3b7edd1303e7e8eb2658e23ae","index":{"nums":[1,927,0,349,309,63,155],"html_filename":"MythTV_dataheap_py.html","relative_filename":"MythTV/dataheap.py"}},"MythTV_exceptions_py":{"hash":"a84c8b17e490c68a3cadcb982c19c653","index":{"nums":[1,126,0,94,52,7,43],"html_filename":"MythTV_exceptions_py.html","relative_filename":"MythTV/exceptions.py"}},"MythTV_logging_py":{"hash":"a1d0e1608ecfd0f0abaea031bafeb8e2","index":{"nums":[1,255,0,95,122,16,80],"html_filename":"MythTV_logging_py.html","relative_filename":"MythTV/logging.py"}},"MythTV_methodheap_py":{"hash":"18dad4ade28465ef80461058ac1d2e10","index":{"nums":[1,651,0,186,304,61,149],"html_filename":"MythTV_methodheap_py.html","relative_filename":"MythTV/methodheap.py"}},"MythTV_msearch_py":{"hash":"62a76bc2b0bbd37e9b43f53277062dc7","index":{"nums":[1,69,0,7,28,6,8],"html_filename":"MythTV_msearch_py.html","relative_filename":"MythTV/msearch.py"}},"MythTV_mythproto_py":{"hash":"7b3b22825c82181ff46054f420e49e6f","index":{"nums":[1,610,0,179,278,53,143],"html_filename":"MythTV_mythproto_py.html","relative_filename":"MythTV/mythproto.py"}},"MythTV_static_py":{"hash":"3241b3776949ca411e601d006018bfcc","index":{"nums":[1,235,0,0,0,0,0],"html_filename":"MythTV_static_py.html","relative_filename":"MythTV/static.py"}},"MythTV_system_py":{"hash":"88b85d070b0f225e95d22d03ea428cdf","index":{"nums":[1,281,0,40,142,18,42],"html_filename":"MythTV_system_py.html","relative_filename":"MythTV/system.py"}},"MythTV_utility___init___py":{"hash":"af5a4cd1b20ece750b418998d2db43f1","index":{"nums":[1,7,0,0,0,0,0],"html_filename":"MythTV_utility___init___py.html","relative_filename":"MythTV/utility/__init__.py"}},"MythTV_utility_altdict_py":{"hash":"c6bb737f7adc7e8bf7a85b6f92598b1e","index":{"nums":[1,103,0,75,14,0,14],"html_filename":"MythTV_utility_altdict_py.html","relative_filename":"MythTV/utility/altdict.py"}},"MythTV_utility_dequebuffer_py":{"hash":"0b13ea9e43a7d7ba68a2f2be382f18cb","index":{"nums":[1,232,0,92,74,15,47],"html_filename":"MythTV_utility_dequebuffer_py.html","relative_filename":"MythTV/utility/dequebuffer.py"}},"MythTV_utility_dicttoxml_py":{"hash":"d2dbca5608dd5c3d3acec4e64ace4b56","index":{"nums":[1,200,0,200,90,0,90],"html_filename":"MythTV_utility_dicttoxml_py.html","relative_filename":"MythTV/utility/dicttoxml.py"}},"MythTV_utility_dt_py":{"hash":"5f2f15afb49fbdd3c07155d91d3a3b73","index":{"nums":[1,315,0,47,142,23,43],"html_filename":"MythTV_utility_dt_py.html","relative_filename":"MythTV/utility/dt.py"}},"MythTV_utility_enum_py":{"hash":"22c033f546be666851227b4edeb21c5b","index":{"nums":[1,82,0,35,58,17,35],"html_filename":"MythTV_utility_enum_py.html","relative_filename":"MythTV/utility/enum.py"}},"MythTV_utility_mixin_py":{"hash":"611d7c3b394074ed41cc97c39f6d1f0b","index":{"nums":[1,128,0,113,101,3,98],"html_filename":"MythTV_utility_mixin_py.html","relative_filename":"MythTV/utility/mixin.py"}},"MythTV_utility_other_py":{"hash":"9b9cd282450001fcffb0c5b3d5ed287a","index":{"nums":[1,397,0,121,185,30,91],"html_filename":"MythTV_utility_other_py.html","relative_filename":"MythTV/utility/other.py"}},"MythTV_utility_singleton_py":{"hash":"9c5bf7bb4e50e96b240bde0a0e912a8c","index":{"nums":[1,45,0,24,14,1,11],"html_filename":"MythTV_utility_singleton_py.html","relative_filename":"MythTV/utility/singleton.py"}}}}